odoo9_addon_knowledge-9.0.1.1.0.99.dev29-py3.8-nspkg.pth
odoo_addons/knowledge/README.rst
odoo_addons/knowledge/__init__.py
odoo_addons/knowledge/__openerp__.py
odoo_addons/knowledge/data/knowledge_data.xml
odoo_addons/knowledge/demo/knowledge.xml
odoo_addons/knowledge/i18n/am.po
odoo_addons/knowledge/i18n/ar.po
odoo_addons/knowledge/i18n/bg.po
odoo_addons/knowledge/i18n/bs.po
odoo_addons/knowledge/i18n/ca.po
odoo_addons/knowledge/i18n/ca_ES.po
odoo_addons/knowledge/i18n/cs.po
odoo_addons/knowledge/i18n/da.po
odoo_addons/knowledge/i18n/de.po
odoo_addons/knowledge/i18n/el.po
odoo_addons/knowledge/i18n/el_GR.po
odoo_addons/knowledge/i18n/en_AU.po
odoo_addons/knowledge/i18n/en_GB.po
odoo_addons/knowledge/i18n/es.po
odoo_addons/knowledge/i18n/es_AR.po
odoo_addons/knowledge/i18n/es_CL.po
odoo_addons/knowledge/i18n/es_CO.po
odoo_addons/knowledge/i18n/es_CR.po
odoo_addons/knowledge/i18n/es_DO.po
odoo_addons/knowledge/i18n/es_EC.po
odoo_addons/knowledge/i18n/es_ES.po
odoo_addons/knowledge/i18n/es_MX.po
odoo_addons/knowledge/i18n/es_PE.po
odoo_addons/knowledge/i18n/es_PY.po
odoo_addons/knowledge/i18n/es_VE.po
odoo_addons/knowledge/i18n/et.po
odoo_addons/knowledge/i18n/eu.po
odoo_addons/knowledge/i18n/fa.po
odoo_addons/knowledge/i18n/fi.po
odoo_addons/knowledge/i18n/fr.po
odoo_addons/knowledge/i18n/fr_CA.po
odoo_addons/knowledge/i18n/fr_CH.po
odoo_addons/knowledge/i18n/fr_FR.po
odoo_addons/knowledge/i18n/gl.po
odoo_addons/knowledge/i18n/gl_ES.po
odoo_addons/knowledge/i18n/gu.po
odoo_addons/knowledge/i18n/he.po
odoo_addons/knowledge/i18n/hi.po
odoo_addons/knowledge/i18n/hr.po
odoo_addons/knowledge/i18n/hr_HR.po
odoo_addons/knowledge/i18n/hu.po
odoo_addons/knowledge/i18n/hy.po
odoo_addons/knowledge/i18n/id.po
odoo_addons/knowledge/i18n/is.po
odoo_addons/knowledge/i18n/it.po
odoo_addons/knowledge/i18n/ja.po
odoo_addons/knowledge/i18n/ka.po
odoo_addons/knowledge/i18n/kab.po
odoo_addons/knowledge/i18n/kk.po
odoo_addons/knowledge/i18n/knowledge.pot
odoo_addons/knowledge/i18n/ko.po
odoo9_addon_knowledge-9.0.1.1.0.99.dev29.dist-info/METADATA
odoo9_addon_knowledge-9.0.1.1.0.99.dev29.dist-info/WHEEL
odoo9_addon_knowledge-9.0.1.1.0.99.dev29.dist-info/namespace_packages.txt
odoo9_addon_knowledge-9.0.1.1.0.99.dev29.dist-info/top_level.txt
odoo9_addon_knowledge-9.0.1.1.0.99.dev29.dist-info/RECORD
